{
  "name": "Agent Expense Tracker - WhatsApp Notifications",
  "nodes": [
    {
      "parameters": {
        "httpMethod": "POST",
        "path": "expense-notification",
        "responseMode": "responseNode",
        "options": {}
      },
      "id": "webhook-trigger",
      "name": "Webhook",
      "type": "n8n-nodes-base.webhook",
      "typeVersion": 1.1,
      "position": [250, 300],
      "webhookId": "expense-notification"
    },
    {
      "parameters": {
        "conditions": {
          "string": [
            {
              "value1": "={{ $json.type }}",
              "operation": "isNotEmpty"
            }
          ]
        }
      },
      "id": "validate-input",
      "name": "Validate Input",
      "type": "n8n-nodes-base.if",
      "typeVersion": 1,
      "position": [450, 300]
    },
    {
      "parameters": {
        "method": "POST",
        "url": "http://localhost:3001/api/sendText",
        "sendHeaders": true,
        "headerParameters": {
          "parameters": [
            {
              "name": "Content-Type",
              "value": "application/json"
            }
          ]
        },
        "sendBody": true,
        "specifyBody": "json",
        "jsonBody": "={\n  \"chatId\": \"Company Expenses\",\n  \"text\": \"{{ $json.message }}\",\n  \"session\": \"default\"\n}"
      },
      "id": "send-whatsapp",
      "name": "Send WhatsApp Message",
      "type": "n8n-nodes-base.httpRequest",
      "typeVersion": 4.1,
      "position": [650, 200]
    },
    {
      "parameters": {
        "respondWith": "json",
        "responseBody": "={{ JSON.stringify({ success: true, message: 'Notification sent' }) }}",
        "options": {}
      },
      "id": "success-response",
      "name": "Success Response",
      "type": "n8n-nodes-base.respondToWebhook",
      "typeVersion": 1,
      "position": [850, 200]
    },
    {
      "parameters": {
        "respondWith": "json",
        "responseBody": "={{ JSON.stringify({ success: false, error: 'Invalid input' }) }}",
        "options": {
          "responseCode": 400
        }
      },
      "id": "error-response",
      "name": "Error Response",
      "type": "n8n-nodes-base.respondToWebhook",
      "typeVersion": 1,
      "position": [650, 400]
    }
  ],
  "connections": {
    "webhook-trigger": {
      "main": [
        [
          {
            "node": "validate-input",
            "type": "main",
            "index": 0
          }
        ]
      ]
    },
    "validate-input": {
      "main": [
        [
          {
            "node": "send-whatsapp",
            "type": "main",
            "index": 0
          }
        ],
        [
          {
            "node": "error-response",
            "type": "main",
            "index": 0
          }
        ]
      ]
    },
    "send-whatsapp": {
      "main": [
        [
          {
            "node": "success-response",
            "type": "main",
            "index": 0
          }
        ]
      ]
    }
  },
  "active": true,
  "settings": {
    "executionOrder": "v1"
  },
  "tags": [
    {
      "name": "Expense Tracker"
    }
  ]
}
